{
  "accuracy": {
      ".metric": "accuracy",
      ".estimator": "binary",
      ".estimate": 0.9199
    },
  "kep": {
      ".metric": "kap",
      ".estimator": "binary",
      ".estimate": 0.3908
    },
  "precision": {
      ".metric": "precision",
      ".estimator": "binary",
      ".estimate": 0.9224
    },
  "roc_auc_false": {
      ".metric": "roc_auc",
      ".estimator": "binary",
      ".estimate": 0.9082
    },
  "roc_auc_true": {
      ".metric": "roc_auc",
      ".estimator": "binary",
      ".estimate": 0.0918
    }
}
